{"average_2weeks":0,"median_2weeks":0,"initialprice":"999","languages":"English, French, German, Italian, Spanish - Spain","userscore":43,"discount":"0","owners":"200,000 .. 500,000","positive":343,"median_forever":93,"average_forever":247,"tags":{"Action":67,"Adventure":15,"Multiplayer":24,"Stealth":82,"Singleplayer":22,"Third Person":41},"negative":426,"ccu":6,"price":"999","appid":13580,"name":"Tom Clancy's Splinter Cell Double Agent","genre":"Action","publisher":"Ubisoft","developer":"Ubisoft Montreal","score_rank":6}