{"average_2weeks":153,"median_2weeks":250,"initialprice":"0","languages":"English, Danish, Dutch, Finnish, French, German, Norwegian, Portuguese, Russian, Spanish - Spain, Swedish","userscore":86,"discount":"0","owners":"500,000 .. 1,000,000","positive":3760,"median_forever":60,"average_forever":480,"tags":{"Shooter":30,"Action":136,"Indie":83,"Mod":73,"FPS":78,"RPG":26,"Pirates":127,"Massively Multiplayer":28,"Free to Play":198,"PvP":41,"Hack and Slash":74,"First-Person":66,"Memes":27,"Medieval":128,"Multiplayer":136,"Singleplayer":39,"Funny":83,"Swordplay":77,"Fast-Paced":46,"Historical":52},"negative":567,"ccu":56,"price":"0","appid":17570,"name":"Pirates, Vikings, and Knights II","genre":"Action, Free to Play, Indie","publisher":"Octoshark Studios","developer":"Octoshark Studios","score_rank":64}