{"average_2weeks":148,"median_2weeks":148,"initialprice":"999","languages":"English, German, French, Italian, Spanish - Spain, Japanese","userscore":90,"discount":"0","owners":"200,000 .. 500,000","positive":1136,"median_forever":47,"average_forever":148,"tags":{"Action":86,"Indie":39,"Adventure":21,"Experimental":26,"RPG":126,"Casual":65,"Retro":48,"Parody ":65,"2D":39,"Puzzle":35,"Anime":14,"Pixel Graphics":16,"Multiplayer":15,"Fantasy":37,"Singleplayer":31,"Comedy":61,"Funny":15,"Great Soundtrack":15,"Fast-Paced":60,"JRPG":63},"negative":166,"ccu":3,"price":"999","appid":214830,"name":"Half Minute Hero: Super Mega Neo Climax Ultimate Boy","genre":"Action, Casual, RPG","publisher":"Marvelous","developer":"Opus","score_rank":67}