{"average_2weeks":102,"median_2weeks":199,"initialprice":"999","languages":"English","userscore":93,"discount":"0","owners":"1,000,000 .. 2,000,000","positive":3373,"median_forever":44,"average_forever":144,"tags":{"Building":47,"Indie":323,"Cute":69,"Touch-Friendly":35,"Surreal":28,"Casual":155,"Classic":30,"Physics":276,"Atmospheric":40,"Masterpiece":46,"2D":128,"Puzzle":388,"Difficult":20,"Story Rich":20,"Singleplayer":208,"Satire":40,"Strategy":30,"Comedy":92,"Great Soundtrack":185,"Funny":41},"negative":230,"ccu":14,"price":"999","appid":22000,"name":"World of Goo","genre":"Indie","publisher":"2D BOY","developer":"2D BOY","score_rank":86}