{"average_2weeks":5,"median_2weeks":10,"initialprice":"3499","languages":"English, German, French, Italian, Korean, Spanish - Spain, Simplified Chinese, Traditional Chinese, Russian, Japanese, Portuguese, Polish, Danish, Dutch, Finnish, Norwegian, Swedish, Hungarian, Czech, Romanian, Turkish, Arabic, Portuguese - Brazil, Bulgarian, Greek, Thai, Ukrainian","userscore":92,"discount":"0","owners":"100,000 .. 200,000","positive":590,"median_forever":15,"average_forever":19,"tags":{"Utilities":44},"negative":57,"ccu":2,"price":"3499","appid":227260,"name":"DisplayFusion","genre":"Utilities","publisher":"Binary Fortress Software","developer":"Binary Fortress Software","score_rank":79}