{"average_2weeks":70,"median_2weeks":70,"initialprice":"499","languages":"English","userscore":71,"discount":"0","owners":"100,000 .. 200,000","positive":2523,"median_forever":152,"average_forever":251,"tags":{"Building":146,"Action":59,"Adventure":202,"Indie":146,"Horror":38,"Underwater":205,"FPS":46,"Exploration":142,"Casual":39,"Open World":236,"Crafting":194,"Survival":339,"First-Person":144,"Sandbox":204,"Atmospheric":77,"Multiplayer":93,"Simulation":70,"Singleplayer":120,"Strategy":26,"Short":33},"negative":990,"ccu":10,"price":"499","appid":286340,"name":"FarSky","genre":"Adventure, Indie","publisher":"Farsky Interactive","developer":"Farsky Interactive","score_rank":32}