{"average_2weeks":188,"median_2weeks":188,"initialprice":"4999","languages":"English, Japanese, Korean, Traditional Chinese, Simplified Chinese","userscore":85,"discount":"0","owners":"0 .. 20,000","positive":383,"median_forever":2626,"average_forever":2303,"tags":{"Design & Illustration":70,"Anime":35,"Photo Editing":47,"Software":39},"negative":55,"ccu":42,"price":"4999","appid":301610,"name":"openCanvas 6","genre":"Design & Illustration, Photo Editing","publisher":"PGN Inc","developer":"PGN Inc","score_rank":67}