{"average_2weeks":154,"median_2weeks":118,"initialprice":"4499","languages":"English, French, Italian, German, Spanish - Spain, Japanese, Korean, Polish, Russian, Simplified Chinese, Portuguese - Brazil","userscore":86,"discount":"0","owners":"500,000 .. 1,000,000","positive":8012,"median_forever":234,"average_forever":410,"tags":{"Co-op":184,"Shooter":120,"Action":197,"Third-Person Shooter":163,"Horror":159,"Female Protagonist":49,"Zombies":371,"FPS":60,"War":74,"Survival Horror":83,"Open World":59,"Survival":138,"Sniper":156,"First-Person":49,"Multiplayer":166,"Singleplayer":110,"Gore":138,"Post-apocalyptic":100,"World War II":170,"Third Person":75},"negative":1208,"ccu":307,"price":"4499","appid":301640,"name":"Zombie Army Trilogy","genre":"Action","publisher":"Rebellion","developer":"Rebellion","score_rank":64}