{"average_2weeks":19,"median_2weeks":38,"initialprice":"1999","languages":"English, French, German, Polish, Russian","userscore":77,"discount":"0","owners":"200,000 .. 500,000","positive":2021,"median_forever":295,"average_forever":412,"tags":{"Tactical":42,"Action":39,"Adventure":54,"Indie":46,"Horror":39,"RPG":75,"Turn-Based Strategy":84,"Open World":15,"Survival":17,"Turn-Based":44,"Atmospheric":25,"Western":90,"Isometric":24,"Turn-Based Combat":63,"Kickstarter":16,"Strategy":85,"Singleplayer":32,"Gore":19,"Turn-Based Tactics":31,"Third Person":11},"negative":556,"ccu":42,"price":"1999","appid":307670,"name":"Hard West","genre":"Adventure, Indie, RPG, Strategy","publisher":"Good Shepherd Entertainment","developer":"CreativeForge Games","score_rank":45}