{"average_2weeks":0,"median_2weeks":0,"initialprice":"0","languages":"English (full audio), French (Subtitles), German  (Subtitles), Italian  (Subtitles), Spanish  (Subtitles)","userscore":0,"discount":"0","owners":"0 .. 20,000","positive":0,"median_forever":124,"average_forever":128,"tags":[],"negative":0,"ccu":1,"price":"0","appid":31130,"name":"Wallace & Gromits Grand Adventures, Episode 4: The Bogey Man","genre":"Adventure","publisher":"Telltale Games","developer":"Telltale Games","score_rank":""}