{"average_2weeks":234,"median_2weeks":455,"initialprice":"1999","languages":"English, Danish, Swedish, French, German, Spanish - Spain, Russian, Italian, Polish, Czech","userscore":79,"discount":"0","owners":"100,000 .. 200,000","positive":1741,"median_forever":119,"average_forever":329,"tags":{"Space":56,"Adventure":101,"Indie":48,"Horror":46,"Exploration":99,"Survival Horror":80,"Open World":36,"Crafting":24,"Survival":136,"Psychological Horror":25,"First-Person":69,"Atmospheric":56,"Sandbox":8,"Sci-fi":84,"Simulation":47,"Story Rich":50,"Singleplayer":79,"Mystery":25,"VR":81,"Walking Simulator":37},"negative":426,"ccu":10,"price":"1999","appid":313630,"name":"The Solus Project","genre":"Adventure, Indie, Simulation","publisher":"Teotl Studios","developer":"Hourences, Grip Games","score_rank":49}