{"average_2weeks":0,"median_2weeks":0,"initialprice":"0","languages":"English, Italian, Spanish, Russian, Simplified Chinese, Czech, Hungarian, Polish, Portuguese, Romanian, Turkish, Bulgarian, German, Portuguese-Brazil, Swedish, Ukrainian","userscore":91,"discount":"0","owners":"0 .. 20,000","positive":354,"median_forever":87,"average_forever":126,"tags":{"Action":30,"Indie":31,"Mod":24,"Puzzle":23,"Difficult":11,"Singleplayer":9,"Free to Play":43,"First-Person":13},"negative":31,"ccu":8,"price":"0","appid":317790,"name":"Rexaura","genre":"Action, Free to Play, Indie","publisher":"Benjamin Bryant","developer":"Benjamin Bryant","score_rank":79}