{"average_2weeks":1,"median_2weeks":1,"initialprice":"999","languages":"English, French, Italian, German, Spanish - Spain, Hungarian, Polish, Russian, Norwegian","userscore":71,"discount":"0","owners":"100,000 .. 200,000","positive":1144,"median_forever":188,"average_forever":209,"tags":{"Chess":191,"Tactical":155,"Action":54,"Indie":164,"Games Workshop":142,"Turn-Based Strategy":178,"Turn-Based":126,"Competitive":121,"Board Game":116,"Sci-fi":154,"Warhammer 40K":258,"Multiplayer":158,"Asynchronous Multiplayer":148,"Strategy":224,"Singleplayer":144,"Gore":183,"Great Soundtrack":111,"Turn-Based Tactics":161,"Early Access":71,"Third Person":55},"negative":460,"ccu":8,"price":"999","appid":322910,"name":"Warhammer 40,000: Regicide","genre":"Action, Indie, Strategy","publisher":"Hammerfall Publishing","developer":"Hammerfall Publishing","score_rank":32}