{"average_2weeks":22,"median_2weeks":26,"initialprice":"1299","languages":"English, French, Italian, German, Spanish - Spain, Portuguese - Brazil, Russian, Japanese, Polish","userscore":77,"discount":"0","owners":"500,000 .. 1,000,000","positive":4034,"median_forever":91,"average_forever":213,"tags":{"Action":113,"Adventure":186,"Indie":158,"Cute":84,"Epic":12,"Intentionally Awkward Controls":15,"Casual":72,"Controller":116,"Physics":198,"Family Friendly":28,"Masterpiece":15,"Simulation":265,"Difficult":160,"3D Platformer":11,"Singleplayer":138,"Comedy":201,"Funny":256,"Third Person":30,"Early Access":13},"negative":1165,"ccu":9,"price":"1299","appid":327890,"name":"I am Bread","genre":"Action, Adventure, Indie, Simulation","publisher":"Bossa Studios","developer":"Bossa Studios","score_rank":43}