{"average_2weeks":0,"median_2weeks":0,"initialprice":"0","languages":"English, French, German, Spanish - Spain, Polish, Russian, Simplified Chinese","userscore":0,"discount":"0","owners":"0 .. 20,000","positive":33,"median_forever":34,"average_forever":34,"tags":{"Rogue-like":23,"Action":34,"Indie":36,"Adventure":28,"Pixel Graphics":23,"RPG":32,"Violent":20,"Rogue-lite":10},"negative":0,"ccu":0,"price":"0","appid":330020,"name":"Children of Morta","genre":"Action, Adventure, Indie, RPG","publisher":"11 bit studios","developer":"Dead Mage","score_rank":""}