{"average_2weeks":0,"median_2weeks":0,"initialprice":"1499","languages":"English, French, German, Japanese, Korean, Russian, Spanish - Spain, Portuguese, Simplified Chinese","userscore":89,"discount":"0","owners":"0 .. 20,000","positive":80,"median_forever":247,"average_forever":189,"tags":{"Adventure":31,"Indie":31,"Puzzle":10,"Casual":34,"VR":6},"negative":9,"ccu":0,"price":"1499","appid":331460,"name":"Rooms: The Unsolvable Puzzle","genre":"Adventure, Casual, Indie","publisher":"HandMade Game","developer":"HandMade Game","score_rank":73}