{"average_2weeks":90,"median_2weeks":90,"initialprice":"999","languages":"English","userscore":81,"discount":"0","owners":"0 .. 20,000","positive":106,"median_forever":252,"average_forever":204,"tags":{"Indie":50,"Adventure":24,"RPG":49,"Exploration":28,"Casual":34,"Replay Value":24,"Anime":9,"Story Rich":14,"Strategy":23,"Great Soundtrack":22,"Funny":12,"JRPG":26,"RPGMaker":38},"negative":15,"ccu":4,"price":"999","appid":332390,"name":"Undefeated","genre":"Adventure, Casual, Indie, RPG, Strategy","publisher":"Aldorlea Games","developer":"Aldorlea Games","score_rank":67}