{"average_2weeks":0,"median_2weeks":0,"initialprice":"1999","languages":"English, French, German, Italian, Russian, Spanish - Spain, Portuguese, Portuguese - Brazil, Traditional Chinese, Turkish, Czech, Hungarian","userscore":59,"discount":"0","owners":"500,000 .. 1,000,000","positive":3494,"median_forever":132,"average_forever":562,"tags":{"Space":138,"Co-op":112,"Shooter":50,"Futuristic":31,"Action":109,"Adventure":127,"Indie":67,"RPG":99,"Massively Multiplayer":44,"Open World":222,"Crafting":153,"Survival":233,"Sandbox":184,"Sci-fi":95,"Multiplayer":176,"Base-Building":191,"Singleplayer":37,"Early Access":97,"Third Person":79},"negative":2872,"ccu":4,"price":"1999","appid":332500,"name":"GRAV","genre":"Action, Adventure, Indie, RPG, Early Access","publisher":"BitMonster, Inc.","developer":"BitMonster, Inc.","score_rank":12}