{"average_2weeks":0,"median_2weeks":0,"initialprice":"299","languages":"English, French, German, Spanish - Spain, Japanese, Polish, Russian, Simplified Chinese","userscore":77,"discount":"0","owners":"100,000 .. 200,000","positive":237,"median_forever":184,"average_forever":173,"tags":{"Action":29,"2D":7,"Anime":32,"Indie":31,"Adventure":29,"Puzzle":19,"Female Protagonist":19,"Puzzle-Platformer":8,"Casual":30,"Vampire":25},"negative":78,"ccu":1,"price":"299","appid":337420,"name":"Final Dusk","genre":"Action, Adventure, Casual, Indie","publisher":"Light Echo","developer":"Light Echo","score_rank":39}