{"average_2weeks":71,"median_2weeks":71,"initialprice":"499","languages":"English, Hungarian, Spanish - Spain, French, Russian, German, Italian, Turkish","userscore":79,"discount":"0","owners":"200,000 .. 500,000","positive":1540,"median_forever":148,"average_forever":304,"tags":{"Co-op":29,"Action":79,"Adventure":65,"Indie":56,"Horror":8,"Zombies":117,"RPG":99,"Violent":21,"Survival Horror":21,"Open World":80,"Crafting":17,"Survival":152,"Sandbox":55,"Simulation":54,"Multiplayer":39,"Top-Down":18,"Strategy":72,"Base-Building":53,"Singleplayer":21,"Post-apocalyptic":46},"negative":402,"ccu":24,"price":"499","appid":340050,"name":"Survivalist","genre":"Action, Adventure, Indie, RPG, Simulation, Strategy","publisher":"Ginormocorp Holdings Ltd","developer":"Bob the Game Development Bot","score_rank":47}