{"average_2weeks":0,"median_2weeks":0,"initialprice":"0","languages":"English, French, German, Russian","userscore":0,"discount":"0","owners":"0 .. 20,000","positive":1637,"median_forever":58,"average_forever":205,"tags":{"Co-op":50,"Fighting":12,"Action":115,"Adventure":33,"MOBA":119,"Batman":98,"Massively Multiplayer":39,"Free to Play":252,"Comic Book":31,"PvP":12,"Open World":7,"Superhero":139,"Multiplayer":104,"Strategy":82,"Third Person":17},"negative":530,"ccu":71,"price":"0","appid":345520,"name":"Infinite Crisis","genre":"Action, Free to Play, Strategy","publisher":"Warner Bros. Interactive Entertainment","developer":"Turbine, Inc.","score_rank":""}