{"average_2weeks":300,"median_2weeks":300,"initialprice":"1299","languages":"English, Russian, Ukrainian, German, Polish, Spanish - Spain, French, Turkish","userscore":70,"discount":"0","owners":"20,000 .. 50,000","positive":905,"median_forever":256,"average_forever":232,"tags":{"Adventure":75,"Indie":56,"Female Protagonist":8,"Nudity":21,"Exploration":41,"Open World":35,"First-Person":49,"Atmospheric":51,"Sci-fi":64,"Puzzle":39,"Cyberpunk":27,"Story Rich":29,"Singleplayer":30,"Great Soundtrack":10,"Walking Simulator":24,"Short":10},"negative":349,"ccu":6,"price":"1299","appid":361550,"name":"Cradle","genre":"Adventure, Indie","publisher":"Flying Cafe for Semianimals","developer":"Flying Cafe for Semianimals","score_rank":34}