{"average_2weeks":0,"median_2weeks":0,"initialprice":"599","languages":"English, French, Italian, German, Spanish, Japanese, Polish, Portuguese-Brazil, Russian, Simplified Chinese, Traditional Chinese","userscore":81,"discount":"0","owners":"0 .. 20,000","positive":274,"median_forever":0,"average_forever":0,"tags":{"Shooter":15,"Action":63,"Adventure":42,"Zombies":31,"FPS":29},"negative":58,"ccu":0,"price":"599","appid":366849,"name":"Call of Duty: Black Ops III - The Giant Zombies Map","genre":"Action, Adventure","publisher":"Activision","developer":"Treyarch","score_rank":53}