{"average_2weeks":154,"median_2weeks":154,"initialprice":"999","languages":"English, Simplified Chinese","userscore":86,"discount":"0","owners":"20,000 .. 50,000","positive":297,"median_forever":428,"average_forever":481,"tags":{"Rogue-like":15,"2D":7,"Indie":32,"Pixel Graphics":16,"RPG":39,"Singleplayer":13,"Dungeon Crawler":18,"Casual":9,"Turn-Based":6},"negative":43,"ccu":30,"price":"999","appid":368610,"name":"The Enchanted Cave 2","genre":"Indie, RPG","publisher":"dustinaux, Leiting Games","developer":"dustinaux","score_rank":67}