{"average_2weeks":0,"median_2weeks":0,"initialprice":"0","languages":"English, French, Italian, German, Spanish - Spain, Dutch, Russian","userscore":65,"discount":"0","owners":"100,000 .. 200,000","positive":286,"median_forever":25,"average_forever":89,"tags":{"Fighting":23,"Action":38,"Indie":36,"Multiplayer":43,"RPG":34,"Free to Play":59,"Casual":34,"Early Access":40,"Sports":42},"negative":152,"ccu":1,"price":"0","appid":393930,"name":"RoShamBo","genre":"Action, Casual, Free to Play, Indie, RPG, Sports, Early Access","publisher":"Blam! Games LLC","developer":"Blam! Games LLC","score_rank":23}