{"average_2weeks":0,"median_2weeks":0,"initialprice":"1299","languages":"English, Spanish - Spain, Japanese, Korean, Traditional Chinese","userscore":92,"discount":"0","owners":"0 .. 20,000","positive":39,"median_forever":20,"average_forever":20,"tags":{"Space":24,"Shooter":22,"Sci-fi":23,"Action":22,"Indie":33,"Female Protagonist":26,"Local Co-Op":24,"Comic Book":18,"Shoot 'Em Up":31,"Top-Down Shooter":22,"Arcade":27,"Local Multiplayer":23},"negative":2,"ccu":0,"price":"1299","appid":394430,"name":"Dimension Drive","genre":"Action, Indie","publisher":"2Awesome Studio","developer":"2Awesome Studio","score_rank":92}