{"average_2weeks":77,"median_2weeks":44,"initialprice":"0","languages":"English, Simplified Chinese, Traditional Chinese, French, Italian, German, Spanish - Spain, Czech, Danish, Dutch, Finnish, Hungarian, Japanese, Korean, Polish, Portuguese - Brazil, Russian, Swedish, Thai, Turkish","userscore":63,"discount":"0","owners":"5,000,000 .. 10,000,000","positive":4722,"median_forever":24,"average_forever":237,"tags":{"Dinosaurs":780,"Action":498,"Adventure":489,"Indie":227,"RPG":308,"FPS":249,"Massively Multiplayer":472,"Exploration":259,"Free to Play":1153,"Open World":565,"PvP":377,"Crafting":330,"Survival":924,"First-Person":294,"Sandbox":240,"Multiplayer":639,"Dragons":373,"Strategy":280,"Singleplayer":276,"Early Access":412},"negative":3231,"ccu":44,"price":"0","appid":407530,"name":"ARK: Survival Of The Fittest","genre":"Action, Adventure, Indie, Massively Multiplayer, RPG, Strategy","publisher":"Studio Wildcard","developer":"Studio Wildcard, Instinct Games, Efecto Studios, Virtual Basement LLC","score_rank":16}