{"average_2weeks":0,"median_2weeks":0,"initialprice":"0","languages":"English, French, Spanish - Spain, German, Russian, Japanese, Portuguese - Brazil","userscore":79,"discount":"0","owners":"0 .. 20,000","positive":42,"median_forever":211,"average_forever":196,"tags":{"Action":32,"Adventure":33,"Indie":33,"Casual":33,"Free to Play":12},"negative":11,"ccu":0,"price":"0","appid":412230,"name":"Infinitrap Classic: Ohio Jack and The Cup Of Eternity","genre":"Action, Adventure, Casual, Indie","publisher":"Shadebob Games","developer":"Shadebob Games","score_rank":47}