{"average_2weeks":0,"median_2weeks":0,"initialprice":"0","languages":"English, Spanish - Spain, Polish, Simplified Chinese, Japanese, German, French, Italian, Portuguese - Brazil, Swedish, Russian, Korean","userscore":89,"discount":"0","owners":"200,000 .. 500,000","positive":6712,"median_forever":9,"average_forever":112,"tags":{"Indie":87,"Cute":64,"Horror":15,"Nudity":49,"Free to Play":213,"Casual":82,"Psychological Horror":26,"Memes":16,"Visual Novel":154,"2D":16,"Anime":172,"Dating Sim":66,"Singleplayer":67,"Mature":10,"Short":90,"Sexual Content":41},"negative":772,"ccu":3,"price":"0","appid":423880,"name":"Carpe Diem","genre":"Casual, Free to Play, Indie","publisher":"Moonlit Works","developer":"Moonlit Works","score_rank":73}