{"average_2weeks":0,"median_2weeks":0,"initialprice":"1999","languages":"Polish, English, Czech, Hungarian, French, German, Spanish, Italian","userscore":37,"discount":"0","owners":"20,000 .. 50,000","positive":233,"median_forever":278,"average_forever":244,"tags":{"Indie":29,"Simulation":50,"Multiplayer":9,"Driving":8,"Singleplayer":8},"negative":273,"ccu":11,"price":"1999","appid":424590,"name":"Farm Expert 2017","genre":"Indie, Simulation","publisher":"Silden","developer":"Silden","score_rank":7}