{"average_2weeks":0,"median_2weeks":0,"initialprice":"999","languages":"English, Japanese","userscore":58,"discount":"0","owners":"0 .. 20,000","positive":21,"median_forever":1340,"average_forever":706,"tags":{"Visual Novel":12,"Adventure":23,"Anime":10,"RPG":20,"Strategy":19},"negative":14,"ccu":0,"price":"999","appid":425460,"name":"Tokyo Twilight Ghost Hunters Daybreak: Special Gigs","genre":"Adventure, RPG, Strategy","publisher":"PQube Limited","developer":"Arc System Works, TOYBOX Inc.","score_rank":17}