{"average_2weeks":0,"median_2weeks":0,"initialprice":"0","languages":"English, Russian","userscore":89,"discount":"0","owners":"100,000 .. 200,000","positive":1100,"median_forever":26,"average_forever":40,"tags":{"Visual Novel":82,"Anime":78,"Indie":49,"Adventure":42,"Horror":9,"Dating Sim":22,"Nudity":19,"Singleplayer":15,"Free to Play":99,"Casual":35},"negative":126,"ccu":1,"price":"0","appid":431540,"name":"Frosty Kiss","genre":"Adventure, Casual, Free to Play, Indie","publisher":"2Chance Projects","developer":"2Chance Projects, IIchan Eroge Team","score_rank":73}