{"average_2weeks":232,"median_2weeks":461,"initialprice":"499","languages":"English","userscore":62,"discount":"0","owners":"100,000 .. 200,000","positive":383,"median_forever":240,"average_forever":249,"tags":{"Space":12,"Shooter":5,"Action":28,"Indie":28,"Adventure":23,"Side Scroller":5,"RPG":19,"Casual":25,"Bullet Hell":9,"Shoot 'Em Up":16},"negative":183,"ccu":2,"price":"499","appid":444220,"name":"Asteroid Bounty Hunter","genre":"Action, Adventure, Casual, Indie, RPG","publisher":"Just1337 Publisher","developer":"Just1337 Studio","score_rank":25}