{"average_2weeks":0,"median_2weeks":0,"initialprice":"0","languages":"English","userscore":81,"discount":"0","owners":"100,000 .. 200,000","positive":546,"median_forever":19,"average_forever":33,"tags":{"Indie":41,"Adventure":37,"Horror":81,"Multiplayer":5,"Singleplayer":28,"Free to Play":81,"Survival Horror":28,"First-Person":27},"negative":120,"ccu":1,"price":"0","appid":453890,"name":"Black Rose","genre":"Adventure, Free to Play, Indie","publisher":"Sir Bedlam Productions","developer":"Sir Bedlam Productions","score_rank":51}