{"average_2weeks":0,"median_2weeks":0,"initialprice":"499","languages":"English","userscore":47,"discount":"0","owners":"0 .. 20,000","positive":53,"median_forever":217,"average_forever":216,"tags":{"Action":34,"Sci-fi":10,"Indie":33,"Violent":22,"Nudity":21,"Gore":20,"Survival":32,"Early Access":34},"negative":56,"ccu":1,"price":"499","appid":454680,"name":"MetaTron","genre":"Nudity, Violent, Gore, Action, Indie, Early Access","publisher":"TubbyKiD UG (haftungsbeschränkt)","developer":"TubbyKiD UG (haftungsbeschränkt)","score_rank":8}