{"average_2weeks":0,"median_2weeks":0,"initialprice":"1499","languages":"English","userscore":0,"discount":"0","owners":"0 .. 20,000","positive":4,"median_forever":0,"average_forever":0,"tags":{"Design & Illustration":21,"Education":21,"Animation & Modeling":21,"Audio Production":21,"Early Access":21},"negative":0,"ccu":0,"price":"1499","appid":458200,"name":"Rumpus","genre":"Animation & Modeling, Audio Production, Design & Illustration, Education, Early Access","publisher":"Luke Iannini","developer":"Luke Iannini","score_rank":""}