{"average_2weeks":0,"median_2weeks":0,"initialprice":"999","languages":"English","userscore":0,"discount":"0","owners":"0 .. 20,000","positive":6,"median_forever":151,"average_forever":151,"tags":{"Level Editor":14,"Co-op":14,"Action":33,"Indie":32,"Horror":13,"Character Customization":13,"Casual":13,"Controller":13,"Beat 'em up":13,"Arcade":13,"Competitive":13,"Family Friendly":13,"2D":15,"Pixel Graphics":14,"Difficult":13,"Singleplayer":14,"Great Soundtrack":14},"negative":2,"ccu":0,"price":"999","appid":468150,"name":"Trap House","genre":"Action, Indie","publisher":"Hive Mind Studios","developer":"Hive Mind Studios","score_rank":""}