{"average_2weeks":0,"median_2weeks":0,"initialprice":"99","languages":"English, Russian","userscore":27,"discount":"0","owners":"50,000 .. 100,000","positive":43,"median_forever":210,"average_forever":214,"tags":{"Co-op":5,"Action":23,"Indie":22,"Adventure":18,"Simulation":18,"Zombies":10,"Massively Multiplayer":20},"negative":60,"ccu":0,"price":"99","appid":473810,"name":"Killbot","genre":"Action, Adventure, Indie, Massively Multiplayer, Simulation","publisher":"nobodyshot","developer":"nobodyshot","score_rank":5}