{"average_2weeks":0,"median_2weeks":0,"initialprice":"199","languages":"English, Portuguese - Brazil","userscore":18,"discount":"0","owners":"100,000 .. 200,000","positive":99,"median_forever":212,"average_forever":232,"tags":{"Action":25,"Indie":38,"Adventure":36,"Puzzle-Platformer":15,"Casual":38,"Classic":11,"Retro":23,"Arcade":26,"Atmospheric":12,"2D":25,"Puzzle":12,"Pixel Graphics":15,"Stylized":13,"Platformer":33,"Singleplayer":15,"Funny":22,"Action-Adventure":22},"negative":98,"ccu":3,"price":"199","appid":475220,"name":"Kabitis","genre":"Action, Adventure, Casual, Indie","publisher":"André Bertaglia","developer":"André Bertaglia","score_rank":9}