{"average_2weeks":0,"median_2weeks":0,"initialprice":"999","languages":"English, French, German, Spanish, Turkish, Simplified Chinese, Traditional Chinese, Czech, Polish","userscore":90,"discount":"0","owners":"0 .. 20,000","positive":2784,"median_forever":0,"average_forever":0,"tags":{"Tactical":45,"Shooter":17,"Action":96,"RPG":68,"War":58,"Massively Multiplayer":6,"First-Person":62,"Multiplayer":83,"Simulation":34,"Horses":18,"Strategy":51,"Singleplayer":26,"Great Soundtrack":6,"Historical":89,"Third Person":58},"negative":260,"ccu":0,"price":"999","appid":48705,"name":"Mount & Blade: Warband - Napoleonic Wars","genre":"Action, RPG","publisher":"TaleWorlds Entertainment","developer":"TaleWorlds Entertainment, Flying Squirrel Entertainment","score_rank":79}