{"average_2weeks":0,"median_2weeks":0,"initialprice":"1199","languages":"English, French, Italian, German, Spanish - Spain, Portuguese - Brazil, Swedish","userscore":0,"discount":"0","owners":"0 .. 20,000","positive":11,"median_forever":0,"average_forever":0,"tags":{"Action":31,"Adventure":31,"Indie":31,"Cute":20,"Female Protagonist":23,"Puzzle-Platformer":11,"Casual":10,"Controller":11,"Physics":11,"Family Friendly":10,"2D":21,"Puzzle":12,"Platformer":10,"Singleplayer":10,"Great Soundtrack":10},"negative":0,"ccu":0,"price":"1199","appid":489120,"name":"Sling Ming","genre":"Action, Adventure, Indie","publisher":"Good Night Brave Warrior","developer":"Good Night Brave Warrior","score_rank":""}