{"average_2weeks":621,"median_2weeks":178,"initialprice":"0","languages":"English","userscore":83,"discount":"0","owners":"200,000 .. 500,000","positive":661,"median_forever":425,"average_forever":549,"tags":{"Indie":46,"Card Game":37,"Free to Play":34,"Turn-Based Strategy":13,"Turn-Based":15,"Competitive":19,"Visual Novel":12,"RTS":11,"Sci-fi":18,"Replay Value":12,"Puzzle":13,"Simulation":34,"Multiplayer":15,"Story Rich":12,"Strategy":47,"Singleplayer":14,"Turn-Based Tactics":12,"Robots":12,"Early Access":40},"negative":132,"ccu":156,"price":"0","appid":490220,"name":"Prismata","genre":"Free to Play, Indie, Simulation, Strategy, Early Access","publisher":"Lunarch Studios","developer":"Lunarch Studios","score_rank":56}