{"average_2weeks":0,"median_2weeks":0,"initialprice":"0","languages":"English, Russian","userscore":0,"discount":"0","owners":"0 .. 20,000","positive":3,"median_forever":0,"average_forever":0,"tags":{"Indie":21,"Adventure":21,"Horror":10,"Lore-Rich":10,"Casual":21,"Survival Horror":9,"Choices Matter":10,"Survival":10,"First-Person":10,"Atmospheric":10,"2D":10,"Choose Your Own Adventure":9,"Clicker":10,"Dark":10,"Stylized":10,"Singleplayer":10,"Gore":10,"Supernatural":10,"Historical":9,"Hidden Object":10},"negative":6,"ccu":0,"price":"0","appid":498810,"name":"Rescue Lucy - House 23 Escape DLC #1","genre":"Adventure, Casual, Indie","publisher":"OtakuMaker SARL","developer":"Starodymov","score_rank":""}