{"average_2weeks":0,"median_2weeks":0,"initialprice":"899","languages":"English, French, Italian, German, Spanish - Spain, Arabic, Bulgarian, Czech, Danish, Dutch, Finnish, Greek, Hungarian, Japanese, Korean, Norwegian, Polish, Portuguese, Portuguese - Brazil, Romanian, Russian, Simplified Chinese, Swedish, Thai, Traditional Chinese, Turkish, Ukrainian","userscore":50,"discount":"0","owners":"0 .. 20,000","positive":12,"median_forever":19,"average_forever":19,"tags":{"Adventure":22,"Indie":21,"Horror":5,"Violent":21,"VR":15},"negative":16,"ccu":0,"price":"899","appid":517400,"name":"VR Amazing Files: Horror Hospital","genre":"Violent, Adventure, Indie","publisher":"Joygo.Studio","developer":"Joygo.Studio","score_rank":6}