{"average_2weeks":15,"median_2weeks":15,"initialprice":"1999","languages":"English, French, German, Portuguese - Brazil, Simplified Chinese, Korean, Russian, Japanese, Spanish - Spain, Polish, Turkish","userscore":74,"discount":"40","owners":"100,000 .. 200,000","positive":2618,"median_forever":286,"average_forever":484,"tags":{"Co-op":190,"Action":94,"Adventure":205,"Indie":111,"Horror":70,"RPG":78,"Survival Horror":80,"Open World":224,"Crafting":183,"Online Co-Op":134,"Survival":365,"Sandbox":125,"Atmospheric":103,"Multiplayer":230,"Simulation":81,"Difficult":80,"Singleplayer":99,"Strategy":67,"Early Access":72},"negative":912,"ccu":47,"price":"1199","appid":526160,"name":"The Wild Eight","genre":"Action, Adventure, Indie, RPG, Simulation, Early Access","publisher":"HypeTrain Digital","developer":"HypeTrain Digital","score_rank":37}