{"average_2weeks":0,"median_2weeks":0,"initialprice":"1999","languages":"English, French, Italian, German, Spanish, Japanese, Polish, Portuguese-Brazil, Russian, Arabic, Korean, Simplified Chinese, Traditional Chinese","userscore":62,"discount":"0","owners":"0 .. 20,000","positive":135,"median_forever":0,"average_forever":0,"tags":{"Action":21,"Adventure":21,"Violent":21,"Gore":21},"negative":99,"ccu":0,"price":"1999","appid":533110,"name":"Middle-earth: Shadow of War - The Desolation of Mordor Story Expansion","genre":"Violent, Gore, Action, Adventure","publisher":"","developer":"Monolith Productions, Inc.","score_rank":14}