{"average_2weeks":0,"median_2weeks":0,"initialprice":"399","languages":"English","userscore":0,"discount":"0","owners":"0 .. 20,000","positive":16,"median_forever":195,"average_forever":185,"tags":{"Shooter":22,"Action":36,"Indie":33,"Colorful":20,"Rhythm":24,"Casual":21,"Cartoon":10,"Retro":32,"Atmospheric":21,"Arcade":12,"Sci-fi":21,"Top-Down":21,"Music":21,"Singleplayer":22,"Great Soundtrack":22,"Funny":21,"Fast-Paced":20,"Audio Production":21,"1980s":20},"negative":4,"ccu":0,"price":"399","appid":535890,"name":"Stereo Aereo","genre":"Action, Indie","publisher":"Indietopia Games","developer":"The Stonebot Studio","score_rank":""}