{"average_2weeks":0,"median_2weeks":0,"initialprice":"499","languages":"English, French, Italian, German, Spanish - Spain, Dutch, Portuguese, Swedish, Hungarian, Portuguese - Brazil, Russian","userscore":0,"discount":"0","owners":"0 .. 20,000","positive":8,"median_forever":224,"average_forever":535,"tags":{"Adventure":21,"Indie":21,"Puzzle":6,"RPG":21,"Strategy":24,"Casual":23,"Match 3":7},"negative":1,"ccu":0,"price":"499","appid":548320,"name":"Magical Mysteries: Path of the Sorceress","genre":"Adventure, Casual, Indie, RPG, Strategy","publisher":"Alder Games","developer":"Alder Games","score_rank":""}