{"average_2weeks":0,"median_2weeks":0,"initialprice":"1699","languages":"English, Russian, Japanese, Polish, Finnish, Portuguese, Swedish, Turkish, Norwegian, Simplified Chinese, Czech, German, Hungarian, Spanish - Spain, French","userscore":81,"discount":"0","owners":"0 .. 20,000","positive":155,"median_forever":125,"average_forever":117,"tags":{"Action":74,"Adventure":73,"Indie":71,"Puzzle-Platformer":51,"Experimental":37,"Casual":37,"Atmospheric":11,"Family Friendly":35,"Puzzle":50,"Parkour":48,"Anime":33,"Ninja":45,"Difficult":45,"Platformer":19,"Story Rich":44,"Singleplayer":37,"Time Manipulation":49,"Comedy":47,"Funny":54,"Great Soundtrack":47},"negative":30,"ccu":0,"price":"1699","appid":552970,"name":"Sumoman","genre":"Action, Adventure, Indie","publisher":"Tequilabyte Studio","developer":"Tequilabyte Studio","score_rank":56}