{"average_2weeks":286,"median_2weeks":495,"initialprice":"3999","languages":"English, French, German, Russian, Simplified Chinese, Spanish - Spain","userscore":72,"discount":"66","owners":"100,000 .. 200,000","positive":2943,"median_forever":499,"average_forever":1149,"tags":{"Wargame":38,"Tactical":75,"Action":87,"War":68,"Open World":15,"Real Time Tactics":17,"Survival":11,"RTS":144,"Simulation":104,"Multiplayer":89,"Strategy":158,"Singleplayer":34,"Historical":15,"World War II":179,"Military":98},"negative":1107,"ccu":287,"price":"1359","appid":572410,"name":"Steel Division: Normandy 44","genre":"Action, Simulation, Strategy","publisher":"Paradox Interactive","developer":"Eugen Systems","score_rank":34}