{"average_2weeks":234,"median_2weeks":234,"initialprice":"99","languages":"English, Turkish","userscore":25,"discount":"0","owners":"100,000 .. 200,000","positive":186,"median_forever":271,"average_forever":261,"tags":{"Action":25,"Sci-fi":13,"Indie":27,"Adventure":24,"Puzzle":15,"Horror":38,"Simulation":23,"Violent":23,"Strategy":19,"Psychological Horror":17,"First-Person":21,"Atmospheric":15},"negative":367,"ccu":1,"price":"99","appid":576440,"name":"Horror Hospital","genre":"Violent, Action, Adventure, Indie, Simulation, Strategy","publisher":"KNP","developer":"KNP","score_rank":3}