{"average_2weeks":0,"median_2weeks":0,"initialprice":"199","languages":"English","userscore":94,"discount":"0","owners":"0 .. 20,000","positive":22,"median_forever":0,"average_forever":0,"tags":{"Building":12,"Level Editor":11,"Indie":22,"Simulation":23,"Base-Building":11,"Casual":22,"City Builder":12,"VR":13,"VR Only":1,"Sandbox":14},"negative":1,"ccu":0,"price":"199","appid":602630,"name":"Diorama Worlds","genre":"Casual, Indie, Simulation","publisher":"Mixed Reality Worlds","developer":"Mixed Reality Worlds","score_rank":92}