{"average_2weeks":0,"median_2weeks":0,"initialprice":"99","languages":"Russian, English","userscore":88,"discount":"0","owners":"20,000 .. 50,000","positive":164,"median_forever":333,"average_forever":297,"tags":{"Visual Novel":25,"Indie":23,"Adventure":22,"Story Rich":16,"Casual":23,"Free to Play":5,"Great Soundtrack":15,"Atmospheric":15},"negative":28,"ccu":0,"price":"99","appid":620530,"name":"Mirt. Tales of the Cold Land. Chapter one","genre":"Adventure, Casual, Free to Play, Indie","publisher":"Chess no choke games","developer":"Emanon Studios","score_rank":61}