{"average_2weeks":145,"median_2weeks":145,"initialprice":"399","languages":"English, Russian, Italian, Simplified Chinese","userscore":60,"discount":"0","owners":"20,000 .. 50,000","positive":32,"median_forever":313,"average_forever":309,"tags":{"Adventure":25,"Indie":21,"Exploration":13,"Mystery":12,"Walking Simulator":11,"Atmospheric":12},"negative":22,"ccu":0,"price":"399","appid":625370,"name":"A SECOND BEFORE US","genre":"Adventure, Indie","publisher":"DimleTeam","developer":"DimleTeam","score_rank":16}