{"average_2weeks":0,"median_2weeks":0,"initialprice":"0","languages":"English, French, German, Italian, Polish, Spanish - Spain, Russian, Czech","userscore":64,"discount":"0","owners":"200,000 .. 500,000","positive":618,"median_forever":203,"average_forever":1603,"tags":{"Simulation":40,"Flight":25,"Historical":14,"World War II":26},"negative":310,"ccu":6,"price":"0","appid":63950,"name":"IL-2 Sturmovik: Cliffs of Dover","genre":"Simulation","publisher":"1C Entertainment","developer":"1C: Maddox Games","score_rank":24}