{"average_2weeks":8,"median_2weeks":8,"initialprice":"299","languages":"English, Russian, French, Italian, German, Spanish - Spain, Portuguese - Brazil, Simplified Chinese, Japanese","userscore":74,"discount":"0","owners":"0 .. 20,000","positive":66,"median_forever":118,"average_forever":63,"tags":{"Action":24,"Indie":23,"Horror":7,"Stealth":7,"Early Access":24},"negative":27,"ccu":0,"price":"299","appid":647410,"name":"Goodbye My King","genre":"Action, Indie, Early Access","publisher":"Siberian Digital","developer":"GK","score_rank":30}