{"average_2weeks":0,"median_2weeks":0,"initialprice":"499","languages":"English, Italian, Spanish - Spain, Arabic, Portuguese - Brazil, Greek, Traditional Chinese, Korean, Norwegian, Portuguese, Russian, Turkish, Finnish, Swedish","userscore":36,"discount":"0","owners":"20,000 .. 50,000","positive":41,"median_forever":16,"average_forever":14,"tags":{"Action":24,"Indie":23,"Violent":21,"Massively Multiplayer":21,"Casual":24,"Racing":25},"negative":35,"ccu":0,"price":"499","appid":649870,"name":"NitroRage","genre":"Violent, Action, Casual, Indie, Massively Multiplayer, Racing","publisher":"XXXgames","developer":"XXXgames","score_rank":11}