{"average_2weeks":28,"median_2weeks":28,"initialprice":"1499","languages":"English, Japanese, French, Italian, German, Spanish - Spain, Korean, Portuguese - Brazil, Russian, Simplified Chinese, Traditional Chinese","userscore":89,"discount":"0","owners":"0 .. 20,000","positive":28,"median_forever":28,"average_forever":28,"tags":{"Fighting":13,"Action":35,"Indie":25,"Adventure":11,"2D Fighter":14,"Bullet Hell":28,"Shoot 'Em Up":35,"Arcade":15,"Competitive":26,"2D":26,"Sci-fi":17,"Pixel Graphics":28,"Multiplayer":27,"Split Screen":26,"Local Multiplayer":27},"negative":3,"ccu":0,"price":"1499","appid":654100,"name":"Rival Megagun","genre":"Action","publisher":"Degica","developer":"Spacewave Software","score_rank":76}