{"average_2weeks":0,"median_2weeks":0,"initialprice":"999","languages":"English, French, German, Spanish - Spain, Simplified Chinese, Korean, Japanese, Portuguese","userscore":0,"discount":"0","owners":"0 .. 20,000","positive":6,"median_forever":2,"average_forever":2,"tags":{"Adventure":22,"Casual":21,"Hidden Object":5},"negative":1,"ccu":0,"price":"999","appid":663120,"name":"The Rosebud Condominium","genre":"Adventure, Casual","publisher":"Plug In Digital","developer":"Blue Salt Games","score_rank":""}