{"average_2weeks":0,"median_2weeks":0,"initialprice":"399","languages":"English, Simplified Chinese","userscore":0,"discount":"0","owners":"0 .. 20,000","positive":9,"median_forever":0,"average_forever":0,"tags":{"Action":43,"Indie":44,"Adventure":42,"RPG":42,"Exploration":22,"Dungeon Crawler":21,"Metroidvania":24,"Controller":22,"Gothic":22,"Retro":21,"Arcade":22,"2D":25,"Anime":22,"Side Scroller":22,"Pixel Graphics":21,"Dark Fantasy":21,"Platformer":23,"Difficult":21,"Fantasy":21,"Vampire":21},"negative":6,"ccu":0,"price":"399","appid":663290,"name":"Dead by Death","genre":"Action, Adventure, Indie, RPG","publisher":"WILLSH","developer":"Wei Shi, WILLSH","score_rank":""}