{"average_2weeks":0,"median_2weeks":0,"initialprice":"499","languages":"English, French, Italian, German, Spanish - Spain, Portuguese - Brazil, Portuguese","userscore":0,"discount":"0","owners":"0 .. 20,000","positive":7,"median_forever":0,"average_forever":0,"tags":{"Action":23,"2D":11,"Indie":21,"Platformer":12,"Exploration":11,"Singleplayer":11,"Metroidvania":13},"negative":3,"ccu":0,"price":"499","appid":698040,"name":"Legends of the Universe - Cosmic Bounty","genre":"Action, Indie","publisher":"LunarCore Games","developer":"LunarCore Games","score_rank":""}