{"average_2weeks":9,"median_2weeks":9,"initialprice":"299","languages":"English, French, Italian, German, Spanish - Spain, Traditional Chinese, Korean, Portuguese, Russian, Japanese","userscore":91,"discount":"0","owners":"0 .. 20,000","positive":122,"median_forever":70,"average_forever":70,"tags":{"Space":12,"Twin Stick Shooter":12,"Dark Humor":11,"Shooter":11,"Action":35,"Indie":33,"Adventure":12,"Zombies":15,"Colorful":12,"RPG":31,"Violent":14,"Shoot 'Em Up":12,"Memes":17,"Arcade":16,"2D":14,"Sci-fi":12,"Singleplayer":14,"Gore":14,"Great Soundtrack":12,"Fast-Paced":12},"negative":13,"ccu":1,"price":"299","appid":713530,"name":"Armored Kitten","genre":"Action, Indie, RPG","publisher":"Ducat","developer":"Ducat","score_rank":76}