{"average_2weeks":0,"median_2weeks":0,"initialprice":"1499","languages":"English","userscore":0,"discount":"0","owners":"0 .. 20,000","positive":10,"median_forever":0,"average_forever":0,"tags":{"Co-op":12,"Action":22,"Adventure":21,"Multiplayer":13,"Violent":21,"Gore":21,"Survival Horror":13,"Survival":13,"Early Access":22},"negative":10,"ccu":0,"price":"1499","appid":723810,"name":"Don't Bleed","genre":"Violent, Gore, Action, Adventure, Early Access","publisher":"Black Banshee Studios","developer":"Black Banshee Studios","score_rank":""}