{"average_2weeks":0,"median_2weeks":0,"initialprice":"199","languages":"English, French, Italian, German, Spanish - Spain, Arabic, Bulgarian, Portuguese - Brazil, Hungarian, Greek, Danish, Traditional Chinese, Simplified Chinese, Korean, Dutch, Norwegian, Polish, Portuguese, Romanian, Russian, Thai, Turkish, Ukrainian, Finnish, Czech, Swedish, Japanese","userscore":75,"discount":"75","owners":"0 .. 20,000","positive":18,"median_forever":34,"average_forever":34,"tags":{"Adventure":21,"Indie":21,"Platformer":7},"negative":6,"ccu":0,"price":"49","appid":726320,"name":"Girl Blonde","genre":"Adventure, Indie","publisher":"Laush Studio","developer":"Laush Dmitriy Sergeevich","score_rank":39}