{"average_2weeks":0,"median_2weeks":0,"initialprice":"0","languages":"English, French, German, Spanish","userscore":92,"discount":"0","owners":"0 .. 20,000","positive":20662,"median_forever":0,"average_forever":0,"tags":{"Co-op":567,"Action":617,"Adventure":383,"Indie":135,"Action RPG":65,"Magic":330,"RPG":415,"Local Co-Op":235,"Online Co-Op":407,"4 Player Local":142,"Team-Based":71,"Arcade":61,"Multiplayer":411,"Difficult":117,"Fantasy":433,"Singleplayer":104,"Strategy":59,"Comedy":631,"Funny":312,"Local Multiplayer":118},"negative":1695,"ccu":4,"price":"0","appid":73050,"name":"Magicka Demo","genre":"Action, RPG","publisher":"Paradox Interactive","developer":"Arrowhead Game Studios","score_rank":83}