{"average_2weeks":0,"median_2weeks":0,"initialprice":"0","languages":"English, Italian","userscore":0,"discount":"0","owners":"0 .. 20,000","positive":6,"median_forever":0,"average_forever":0,"tags":{"Rogue-like":14,"Mystery Dungeon":15,"Adventure":36,"Indie":33,"Pixel Graphics":23,"Difficult":11,"RPG":33,"Dungeon Crawler":22},"negative":2,"ccu":0,"price":"0","appid":751070,"name":"Pixel Stories of Dungeon Demo","genre":"Adventure, Indie, RPG","publisher":"PowerGaelic","developer":"PowerGaelic","score_rank":""}