{"average_2weeks":0,"median_2weeks":0,"initialprice":"999","languages":"English, French, German, Italian, Spanish - Spain","userscore":65,"discount":"0","owners":"500,000 .. 1,000,000","positive":1076,"median_forever":62,"average_forever":334,"tags":{"Trains":93,"Economy":61,"Simulation":60,"Multiplayer":24,"Real-Time with Pause":15,"Strategy":101,"Singleplayer":26,"Casual":7,"Management":73,"Classic":8},"negative":543,"ccu":124,"price":"999","appid":7600,"name":"Sid Meier's Railroads!","genre":"Strategy","publisher":"2K, Feral Interactive (Mac)","developer":"Firaxis Games, Feral Interactive (Mac)","score_rank":24}