{"average_2weeks":12,"median_2weeks":12,"initialprice":"0","languages":"English, French, German, Simplified Chinese, Russian, Spanish - Spain, Ukrainian, Japanese","userscore":84,"discount":"0","owners":"20,000 .. 50,000","positive":28,"median_forever":34,"average_forever":96,"tags":{"Video Production":13,"Utilities":33,"VR":15,"360 Video":13,"VR Only":1},"negative":5,"ccu":0,"price":"0","appid":768100,"name":"GizmoVR Video Player","genre":"Utilities","publisher":"Gizmo VR LTD","developer":"Gizmo VR LTD","score_rank":59}