{"average_2weeks":17,"median_2weeks":19,"initialprice":"799","languages":"English, French, Italian, German, Spanish - Spain, Bulgarian, Czech, Danish, Dutch, Finnish, Greek, Hungarian, Japanese, Korean, Norwegian, Polish, Portuguese, Romanian, Russian, Simplified Chinese, Swedish, Thai, Traditional Chinese, Turkish, Ukrainian","userscore":87,"discount":"0","owners":"20,000 .. 50,000","positive":602,"median_forever":105,"average_forever":133,"tags":{"Shooter":31,"Realistic":22,"Tactical":21,"Action":33,"Indie":41,"FPS":36,"War":49,"First-Person":22,"Physics":21,"Sandbox":24,"Atmospheric":20,"Team-Based":20,"Simulation":31,"Strategy":52,"Singleplayer":35,"Funny":19,"Historical":30,"Early Access":39,"Military":31},"negative":88,"ccu":7,"price":"799","appid":775940,"name":"Rise of Liberty","genre":"Indie, Strategy, Early Access","publisher":"Sandstorm Studios Inc.","developer":"Sandstorm Studios Inc.","score_rank":67}