{"average_2weeks":0,"median_2weeks":0,"initialprice":"899","languages":"English, Russian","userscore":91,"discount":"0","owners":"0 .. 20,000","positive":41,"median_forever":242,"average_forever":242,"tags":{"Visual Novel":23,"Indie":32,"Adventure":22,"Anime":17,"Female Protagonist":17,"Fantasy":12,"Romance":14,"Casual":33,"Otome":15},"negative":4,"ccu":0,"price":"899","appid":778150,"name":"Crossroad","genre":"Adventure, Casual, Indie","publisher":"TsunamiGames","developer":"kalanhow","score_rank":79}