{"average_2weeks":0,"median_2weeks":0,"initialprice":"999","languages":"English, Japanese, Simplified Chinese, Traditional Chinese, Korean","userscore":80,"discount":"0","owners":"0 .. 20,000","positive":74,"median_forever":210,"average_forever":210,"tags":{"Cute":10,"Simulation":20,"Pixel Graphics":15,"Strategy":21,"Singleplayer":14,"Base-Building":14,"Retro":12},"negative":16,"ccu":8,"price":"999","appid":785780,"name":"OF MICE AND SAND -REVISED-","genre":"Simulation, Strategy","publisher":"ARC SYSTEM WORKS","developer":"ARC SYSTEM WORKS","score_rank":53}