{"average_2weeks":0,"median_2weeks":0,"initialprice":"199","languages":"English","userscore":0,"discount":"50","owners":"0 .. 20,000","positive":21,"median_forever":15,"average_forever":8,"tags":{"Rogue-like":13,"Action":25,"Replay Value":13,"Indie":25,"Difficult":13,"Violent":20,"Gore":23,"Controller":13,"Arcade":14},"negative":16,"ccu":0,"price":"99","appid":785960,"name":"The Binding Of YOU","genre":"Action, Indie","publisher":"StarSystemStudios™","developer":"StarSystemStudios™, Jay Brad Spann","score_rank":""}