{"average_2weeks":0,"median_2weeks":0,"initialprice":"0","languages":"","userscore":95,"discount":"0","owners":"0 .. 20,000","positive":43075,"median_forever":0,"average_forever":0,"tags":{"Rogue-like":1723,"Action":758,"Indie":1585,"Adventure":475,"Addictive":410,"RPG":333,"Dungeon Crawler":267,"Bullet Hell":241,"Rogue-lite":344,"Survival":313,"Atmospheric":182,"Procedural Generation":805,"Replay Value":1075,"2D":273,"Top-Down":590,"Perma Death":262,"Dark":664,"Difficult":996,"Singleplayer":448,"Great Soundtrack":571},"negative":1886,"ccu":0,"price":"0","appid":81096,"name":"The Binding of Isaac Trailer","genre":"Action, Indie","publisher":"","developer":"","score_rank":92}