{"average_2weeks":0,"median_2weeks":0,"initialprice":"0","languages":"","userscore":89,"discount":"0","owners":"0 .. 20,000","positive":955,"median_forever":0,"average_forever":0,"tags":{"Co-op":17,"2D":23,"Indie":73,"Puzzle":42,"Puzzle-Platformer":28,"Platformer":76,"Local Co-Op":26,"Singleplayer":18,"Time Manipulation":16,"Local Multiplayer":16},"negative":148,"ccu":0,"price":"0","appid":81669,"name":"Adventures of Shuggy Trailer","genre":"","publisher":"","developer":"Smudged Cat Games Ltd","score_rank":64}