{"average_2weeks":0,"median_2weeks":0,"initialprice":"399","languages":"English, French, Italian, German, Spanish - Spain, Simplified Chinese, Korean, Portuguese, Russian, Japanese","userscore":0,"discount":"0","owners":"0 .. 20,000","positive":3,"median_forever":1,"average_forever":1,"tags":{"Offroad":40,"Adventure":39,"Simulation":61,"Singleplayer":41,"Racing":51},"negative":6,"ccu":0,"price":"399","appid":838420,"name":"Longboard Stunts and Tricks","genre":"Racing, Simulation","publisher":"Coffee-Powered Games","developer":"Coffee-Powered Games","score_rank":""}