{"average_2weeks":0,"median_2weeks":0,"initialprice":"499","languages":"English, French, Spanish - Spain, Russian","userscore":40,"discount":"0","owners":"0 .. 20,000","positive":7,"median_forever":0,"average_forever":0,"tags":{"Space":13,"Aliens":12,"Indie":32,"Adventure":31,"Space Sim":11,"City Builder":10,"Resource Management":11,"Spectacle fighter":11,"Sandbox":13,"RTS":11,"2D":11,"Sci-fi":10,"Simulation":31,"Strategy":31,"Base-Building":13,"Singleplayer":12,"Early Access":32,"Grand Strategy":11,"Military":10},"negative":6,"ccu":0,"price":"499","appid":868710,"name":"Hope of Humanity","genre":"Adventure, Indie, Simulation, Strategy, Early Access","publisher":"Artepi Corporation","developer":"Artepi Corporation","score_rank":11}