{"average_2weeks":0,"median_2weeks":0,"initialprice":"299","languages":"English, Russian, French, German, Simplified Chinese","userscore":100,"discount":"0","owners":"0 .. 20,000","positive":25,"median_forever":0,"average_forever":0,"tags":{"Action":32,"2D":22,"Indie":42,"Adventure":31,"Platformer":23,"Difficult":15,"Massively Multiplayer":30,"Casual":42},"negative":2,"ccu":0,"price":"299","appid":872580,"name":"The Neon Boy","genre":"Action, Adventure, Casual, Indie, Massively Multiplayer","publisher":"Shenshella","developer":"Shenshella","score_rank":83}