{"average_2weeks":63,"median_2weeks":22,"initialprice":"0","languages":"English, Russian, French, German","userscore":75,"discount":"0","owners":"1,000,000 .. 2,000,000","positive":8328,"median_forever":29,"average_forever":112,"tags":{"Shooter":128,"Co-op":47,"Action":137,"FPS":103,"Violent":76,"Nudity":40,"Massively Multiplayer":145,"Free to Play":240,"Open World":79,"Survival":173,"Psychological Horror":41,"First-Person":54,"Memes":56,"Anime":34,"Multiplayer":167,"Battle Royale":203,"Funny":88,"Early Access":101,"World War II":61},"negative":2717,"ccu":355,"price":"0","appid":884660,"name":"Cuisine Royale","genre":"Action, Free to Play, Massively Multiplayer, Early Access","publisher":"Gaijin Distribution KFT","developer":"Darkflow Software","score_rank":39}