{"average_2weeks":0,"median_2weeks":0,"initialprice":"99","languages":"English, French, Italian, German, Spanish - Spain, Arabic, Bulgarian, Portuguese - Brazil, Hungarian, Greek, Danish, Traditional Chinese, Simplified Chinese, Korean, Dutch, Norwegian, Polish, Portuguese, Romanian, Russian, Thai, Turkish, Ukrainian, Finnish, Czech, Swedish, Japanese","userscore":100,"discount":"0","owners":"0 .. 20,000","positive":27,"median_forever":0,"average_forever":0,"tags":{"Indie":21,"Adventure":20,"Anime":14,"Nudity":24,"Casual":23,"Sexual Content":29},"negative":1,"ccu":0,"price":"99","appid":912190,"name":"Hentai IQ Puzzle","genre":"Adventure, Casual, Indie","publisher":"AFBIK Studio","developer":"AFBIK Studio","score_rank":95}