{"average_2weeks":0,"median_2weeks":0,"initialprice":"499","languages":"English, French, Spanish - Spain, Russian, Traditional Chinese, Italian, German, Polish, Dutch","userscore":0,"discount":"0","owners":"20,000 .. 50,000","positive":80,"median_forever":0,"average_forever":0,"tags":{"Action":32,"Indie":40,"Multiplayer":18,"Strategy":30,"Free to Play":46,"Casual":32,"Early Access":40},"negative":39,"ccu":39,"price":"499","appid":931260,"name":"Multibombers","genre":"Action, Casual, Free to Play, Indie, Strategy, Early Access","publisher":"Pig's Indie Games","developer":"Pig's Indie Games","score_rank":""}