{"average_2weeks":0,"median_2weeks":0,"initialprice":"599","languages":"English, Russian, Italian, German, Simplified Chinese","userscore":92,"discount":"0","owners":"0 .. 20,000","positive":15,"median_forever":0,"average_forever":0,"tags":{"Action":24,"2D":11,"Indie":24,"Anime":11,"GameMaker":10},"negative":1,"ccu":0,"price":"599","appid":958090,"name":"School of the Dead: Anastasia","genre":"Action, Indie","publisher":"NOINDEX GAMES","developer":"NOINDEX GAMES, Maksim Streicher","score_rank":86}