{"average_2weeks":0,"median_2weeks":0,"initialprice":"999","languages":"English, French, Italian, German, Spanish - Spain, Japanese, Korean, Polish, Russian, Simplified Chinese","userscore":0,"discount":"0","owners":"0 .. 20,000","positive":2,"median_forever":0,"average_forever":0,"tags":{"Action":20,"Indie":20,"Racing":20},"negative":0,"ccu":0,"price":"999","appid":967400,"name":"GRIP: Combat Racing - Official Soundtrack","genre":"Action, Indie, Racing","publisher":"Wired Productions","developer":"Caged Element Inc.","score_rank":""}