{"average_2weeks":0,"median_2weeks":0,"initialprice":"499","languages":"English, Spanish - Spain, German, Russian, Simplified Chinese, Japanese, Korean, French, Italian, Hungarian, Polish, Portuguese","userscore":91,"discount":"20","owners":"0 .. 20,000","positive":55,"median_forever":0,"average_forever":0,"tags":{"Action":23,"Indie":22,"Violent":23,"Free to Play":24,"Gore":23},"negative":5,"ccu":0,"price":"399","appid":968390,"name":"Deceit - Vampire Pack","genre":"Action, Free to Play, Indie","publisher":"Automaton","developer":"Automaton","score_rank":79}